README.md
setup.py
wdc
tests/__init__.py
tests/base_client_it.py
tests/test_client_it.py
tests/test_client_resource_it.py
tests/test_client_unit.py
tests/test_connection.py
tests/test_cyrilic_client_it.py
tests/test_exceptions.py
tests/test_multi_client_it.py
tests/test_tailing_slash_client_it.py
webdav3/__init__.py
webdav3/client.py
webdav3/connection.py
webdav3/exceptions.py
webdav3/urn.py
webdavclient3.egg-info/PKG-INFO
webdavclient3.egg-info/SOURCES.txt
webdavclient3.egg-info/dependency_links.txt
webdavclient3.egg-info/requires.txt
webdavclient3.egg-info/top_level.txt