Metadata-Version: 2.1
Name: webdavclient3
Version: 3.14.5
Summary: WebDAV client, based on original package https://github.com/designerror/webdav-client-python but uses requests instead of PyCURL
Home-page: https://github.com/ezhov-evgeny/webdav-client-python-3
Author: Evgeny Ezhov
Author-email: ezhov.evgeny@gmail.com
License: MIT License
Keywords: webdav,client,python,module,library,packet,Yandex.Disk,Dropbox,Google Disk,Box,4shared
Platform: UNKNOWN
Classifier: Environment :: Console
Classifier: Environment :: Web Environment
Classifier: License :: OSI Approved :: MIT License
Classifier: Operating System :: MacOS
Classifier: Operating System :: Microsoft
Classifier: Operating System :: Unix
Classifier: Programming Language :: Python :: 3.5
Classifier: Programming Language :: Python :: 3.6
Classifier: Programming Language :: Python :: 3.7
Classifier: Programming Language :: Python :: 3.8
Classifier: Topic :: Internet
Classifier: Topic :: Software Development :: Libraries :: Python Modules
Requires: python (>= 3.3.0)
